pysaber/__init__.py
pysaber/deblur.py
pysaber/deblursr.py
pysaber/main.py
pysaber/mainsr.py
pysaber/models.py
pysaber/modelssr.py
pysaber/optim.py
pysaber/optimsr.py
pysaber/trans.py
pysaber/transsr.py
pysaber-1.0.0.dist-info/LICENSE
pysaber-1.0.0.dist-info/METADATA
pysaber-1.0.0.dist-info/NOTICE
pysaber-1.0.0.dist-info/WHEEL
pysaber-1.0.0.dist-info/top_level.txt
pysaber-1.0.0.dist-info/RECORD
