Metadata-Version: 2.1
Name: pysaber
Version: 1.0.0
Summary: Python package that implements a systems approach to blur estimation and reduction (SABER)
Home-page: https://github.com/sabersw
Author: K. Aditya Mohan
Author-email: mohan3@llnl.gov
License: MIT
Platform: UNKNOWN
Classifier: Programming Language :: Python :: 3
Classifier: License :: OSI Approved :: MIT License
Classifier: Operating System :: OS Independent
Requires-Dist: numpy
Requires-Dist: pyyaml
Requires-Dist: scipy
Requires-Dist: scikit-image
Requires-Dist: scikit-learn
Requires-Dist: matplotlib
